mylib_015/__init__.py
mylib_015-0.1.dist-info/LICENSE.txt
mylib_015-0.1.dist-info/METADATA
mylib_015-0.1.dist-info/WHEEL
mylib_015-0.1.dist-info/top_level.txt
mylib_015-0.1.dist-info/RECORD
